CONTRIBUTORS.txt
MANIFEST.in
README.rst
requirements.txt
setup.py
tox.ini
gipsy/__init__.py
gipsy/modeltranslation/__init__.py
gipsy/modeltranslation/menus/__init__.py
gipsy/modeltranslation/menus/admin.py
gipsy/modeltranslation/menus/apps.py
gipsy/modeltranslation/menus/forms.py
gipsy/modeltranslation/menus/managers.py
gipsy/modeltranslation/menus/models.py
gipsy/modeltranslation/menus/tests.py
gipsy/modeltranslation/menus/translation.py
gipsy/modeltranslation/menus/migrations/0001_initial.py
gipsy/modeltranslation/menus/migrations/__init__.py
gipsy/modeltranslation/menus/templatetags/__init__.py
gipsy/modeltranslation/menus/templatetags/gipsy_menus.py
gipsy_modeltranslation_menus.egg-info/PKG-INFO
gipsy_modeltranslation_menus.egg-info/SOURCES.txt
gipsy_modeltranslation_menus.egg-info/dependency_links.txt
gipsy_modeltranslation_menus.egg-info/namespace_packages.txt
gipsy_modeltranslation_menus.egg-info/requires.txt
gipsy_modeltranslation_menus.egg-info/top_level.txt
requirements/base.txt
requirements/dev.txt
requirements/production.txt
requirements/test.txt