Metadata-Version: 1.1
Name: gipsy-modeltranslation-menus
Version: 0.1.5
Summary: Gipsy Modeltranslation Menus
Home-page: http://github.com/revsquare/gipsy-modeltranslation-menus
Author: Rafał Selewońko
Author-email: rafal@selewonko.com
License: MIT
Platform: UNKNOWN
Classifier: Operating System :: OS Independent
Classifier: Programming Language :: Python
Classifier: Programming Language :: Python :: 3
Classifier: Programming Language :: Python :: 3.2
Classifier: Programming Language :: Python :: 3.3
Classifier: Programming Language :: Python :: 3.4
Classifier: Topic :: Internet :: WWW/HTTP
